{
  "systemStats": {
    "date": "10 Apr 2024",
    "dayPeakGen": 0.0,
    "eveningPeakGen": 11948.0,
    "dayPeakDemand": 0.0,
    "eveningPeakDemand": 11948.0,
    "minGen": 80000.0,
    "maxGen": 15897.0,
    "totalEnergyGen": 260.562858,
    "totalEnergyUnserved": 0.0,
    "totalEnergyDemand": 260.56,
    "maxTemp": 32.8,
    "totalGasSuppliedPower": 1150.23,
    "avgProductionCost": 4.728,
    "totalDailyCost": 1231926851
  },
  "generationData": [
    {
      "name": "Gas",
      "gen": 0.0,
      "cost": 0,
      "unitCost": 3.45,
      "color": "#0ea5e9"
    },
    {
      "name": "Coal",
      "gen": 0.0,
      "cost": 0,
      "unitCost": 6.62,
      "color": "#64748b"
    },
    {
      "name": "HFO",
      "gen": 0.0,
      "cost": 0,
      "unitCost": 18.06,
      "color": "#f97316"
    },
    {
      "name": "Hydro",
      "gen": 0.0,
      "cost": 0,
      "unitCost": 0.1,
      "color": "#06b6d4"
    },
    {
      "name": "Solar",
      "gen": 0.0,
      "cost": 0,
      "unitCost": 15.77,
      "color": "#eab308"
    },
    {
      "name": "Imports",
      "gen": 44.32,
      "cost": 281013329,
      "unitCost": 6.34,
      "color": "#a855f7"
    },
    {
      "name": "HSD (Diesel)",
      "gen": 0.0,
      "cost": 0,
      "unitCost": 0.0,
      "color": "#ef4444"
    }
  ],
  "borderImportsData": [
    {
      "source": "HVDC Bheramara (India)",
      "energy": 21.88,
      "peakFlow": 0.0,
      "type": "C/B Interconnector (West)"
    },
    {
      "source": "Adani Godda (India)",
      "energy": 20.38,
      "peakFlow": 1018.0,
      "type": "C/B Interconnector (North)"
    },
    {
      "source": "Tripura Cumilla (India)",
      "energy": 2.06,
      "peakFlow": 0.0,
      "type": "C/B Interconnector (East)"
    }
  ],
  "regionalDemandData": [
    {
      "zone": "Dhaka",
      "loadShed": 0.0,
      "demand": 3048.73,
      "pct": 0.0
    },
    {
      "zone": "Chattogram",
      "loadShed": 0.0,
      "demand": 1187.0,
      "pct": 0.0
    },
    {
      "zone": "Cumilla",
      "loadShed": 0.0,
      "demand": 1263.0,
      "pct": 0.0
    },
    {
      "zone": "Mymensingh",
      "loadShed": 0.0,
      "demand": 1151.0,
      "pct": 0.0
    },
    {
      "zone": "Sylhet",
      "loadShed": 0.0,
      "demand": 483.0,
      "pct": 0.0
    },
    {
      "zone": "Khulna",
      "loadShed": 0.0,
      "demand": 1507.4,
      "pct": 0.0
    },
    {
      "zone": "Barishal",
      "loadShed": 0.0,
      "demand": 400.0,
      "pct": 0.0
    },
    {
      "zone": "Rajshahi",
      "loadShed": 0.0,
      "demand": 1411.0,
      "pct": 0.0
    },
    {
      "zone": "Rangpur",
      "loadShed": 0.0,
      "demand": 922.0,
      "pct": 0.0
    }
  ],
  "dailyOutages": [],
  "hourlyLoadData": [
    {
      "time": "00:00",
      "generation": 11430.0,
      "loadShed": 0.0,
      "demand": 11430.0
    },
    {
      "time": "01:00",
      "generation": 11703.0,
      "loadShed": 0.0,
      "demand": 11703.0
    },
    {
      "time": "02:00",
      "generation": 11369.0,
      "loadShed": 0.0,
      "demand": 11369.0
    },
    {
      "time": "03:00",
      "generation": 11175.0,
      "loadShed": 0.0,
      "demand": 11175.0
    },
    {
      "time": "04:00",
      "generation": 10975.0,
      "loadShed": 0.0,
      "demand": 10975.0
    },
    {
      "time": "05:00",
      "generation": 9836.0,
      "loadShed": 0.0,
      "demand": 9836.0
    },
    {
      "time": "06:00",
      "generation": 9170.0,
      "loadShed": 0.0,
      "demand": 9170.0
    },
    {
      "time": "07:00",
      "generation": 8885.0,
      "loadShed": 0.0,
      "demand": 8885.0
    },
    {
      "time": "08:00",
      "generation": 9002.0,
      "loadShed": 0.0,
      "demand": 9002.0
    },
    {
      "time": "09:00",
      "generation": 9172.0,
      "loadShed": 0.0,
      "demand": 9172.0
    },
    {
      "time": "10:00",
      "generation": 9544.0,
      "loadShed": 0.0,
      "demand": 9544.0
    },
    {
      "time": "11:00",
      "generation": 9817.0,
      "loadShed": 0.0,
      "demand": 9817.0
    },
    {
      "time": "12:00",
      "generation": 10049.0,
      "loadShed": 0.0,
      "demand": 10049.0
    },
    {
      "time": "13:00",
      "generation": 10497.0,
      "loadShed": 0.0,
      "demand": 10497.0
    },
    {
      "time": "14:00",
      "generation": 11043.0,
      "loadShed": 0.0,
      "demand": 11043.0
    },
    {
      "time": "15:00",
      "generation": 10932.0,
      "loadShed": 0.0,
      "demand": 10932.0
    },
    {
      "time": "16:00",
      "generation": 10678.0,
      "loadShed": 0.0,
      "demand": 10678.0
    },
    {
      "time": "17:00",
      "generation": 10593.0,
      "loadShed": 0.0,
      "demand": 10593.0
    },
    {
      "time": "18:00",
      "generation": 11023.0,
      "loadShed": 0.0,
      "demand": 11023.0
    },
    {
      "time": "19:00",
      "generation": 11750.0,
      "loadShed": 0.0,
      "demand": 11750.0
    },
    {
      "time": "20:00",
      "generation": 11946.0,
      "loadShed": 0.0,
      "demand": 11946.0
    },
    {
      "time": "21:00",
      "generation": 11771.0,
      "loadShed": 0.0,
      "demand": 11771.0
    },
    {
      "time": "22:00",
      "generation": 11674.0,
      "loadShed": 0.0,
      "demand": 11674.0
    },
    {
      "time": "23:00",
      "generation": 11552.0,
      "loadShed": 0.0,
      "demand": 11552.0
    }
  ],
  "gasProductionData": [
    {
      "company": "BGFCL (Titas, Habiganj, Bakhrabad)",
      "fields": 5,
      "gas": 0.0,
      "condensate": 0.0,
      "share": 0.0
    },
    {
      "company": "SGFL (Sylhet, Rashidpur, Kailashtila)",
      "fields": 5,
      "gas": 0.0,
      "condensate": 0.0,
      "share": 0.0
    },
    {
      "company": "BAPEX (Shahbazpur, Srikail, Begumganj)",
      "fields": 9,
      "gas": 0.0,
      "condensate": 0.0,
      "share": 0.0
    },
    {
      "company": "Chevron (Bibiyana, Jalalabad, Moulavibazar)",
      "fields": 3,
      "gas": 0.0,
      "condensate": 0.0,
      "share": 0.0
    },
    {
      "company": "Tullow (Bangora)",
      "fields": 1,
      "gas": 0.0,
      "condensate": 0.0,
      "share": 0.0
    },
    {
      "company": "RPGCL (R-LNG Import / LNG Terminal)",
      "fields": 0,
      "gas": 0.0,
      "condensate": 0.0,
      "share": 0.0
    }
  ],
  "gasDistributionData": [
    {
      "company": "TGTDCL (Dhaka & Mymensingh)",
      "power": 414.4,
      "fertilizer": 12.2,
      "others": 557.9,
      "total": 984.5
    },
    {
      "company": "BGDCL (Cumilla & Sylhet)",
      "power": 224.1,
      "fertilizer": 0.0,
      "others": 90.3,
      "total": 314.4
    },
    {
      "company": "KGDCL (Chattogram)",
      "power": 76.7,
      "fertilizer": 8.1,
      "others": 90.5,
      "total": 175.2
    },
    {
      "company": "JGTDSL (Sylhet region)",
      "power": 274.1,
      "fertilizer": 2.0,
      "others": 67.2,
      "total": 343.2
    },
    {
      "company": "PGCL (Rajshahi & Rangpur)",
      "power": 99.2,
      "fertilizer": 0.0,
      "others": 13.3,
      "total": 112.5
    },
    {
      "company": "SGCL (Barishal & Khulna)",
      "power": 65.6,
      "fertilizer": 0.0,
      "others": 3.2,
      "total": 68.8
    }
  ]
}